[
  {
    "full_name": "esnet/iperf",
    "stargazers_count": 4957,
    "open_issues_count": 159,
    "forks_count": 1083
  },
  {
    "full_name": "scrapy/scrapy",
    "stargazers_count": 45539,
    "open_issues_count": 768,
    "forks_count": 9819
  },
  {
    "full_name": "home-assistant/core",
    "stargazers_count": 57111,
    "open_issues_count": 2343,
    "forks_count": 21313
  },
  {
    "full_name": "pytorch/pytorch",
    "stargazers_count": 61436,
    "open_issues_count": 10531,
    "forks_count": 17097
  },
  {
    "full_name": "django/django",
    "stargazers_count": 67998,
    "open_issues_count": 158,
    "forks_count": 28401
  },
  {
    "full_name": "Shra1V32/TataSky-Playlist-AutoUpdater",
    "stargazers_count": 293,
    "open_issues_count": 0,
    "forks_count": 48
  },
  {
    "full_name": "sabbiriptv/FIFA-WorldCUP",
    "stargazers_count": 6,
    "open_issues_count": 0,
    "forks_count": 2
  },
  {
    "full_name": "mikeroyal/Apple-Silicon-Guide",
    "stargazers_count": 866,
    "open_issues_count": 4,
    "forks_count": 44
  },
  {
    "full_name": "Sonelli/juicessh-performancemonitor",
    "stargazers_count": 600,
    "open_issues_count": 63,
    "forks_count": 248
  },
  {
    "full_name": "osxfuse/osxfuse",
    "stargazers_count": 7811,
    "open_issues_count": 138,
    "forks_count": 492
  },
  {
    "full_name": "yep/app-downloader",
    "stargazers_count": 238,
    "open_issues_count": 2,
    "forks_count": 16
  },
  {
    "full_name": "rxhanson/Rectangle",
    "stargazers_count": 19825,
    "open_issues_count": 47,
    "forks_count": 575
  },
  {
    "full_name": "iina/iina",
    "stargazers_count": 32109,
    "open_issues_count": 1474,
    "forks_count": 2357
  },
  {
    "full_name": "serhii-londar/open-source-mac-os-apps",
    "stargazers_count": 33630,
    "open_issues_count": 73,
    "forks_count": 2134
  },
  {
    "full_name": "ntop/ntopng",
    "stargazers_count": 5028,
    "open_issues_count": 261,
    "forks_count": 588
  },
  {
    "full_name": "emmericp/MoonGen",
    "stargazers_count": 939,
    "open_issues_count": 76,
    "forks_count": 215
  },
  {
    "full_name": "mitthu786/tvepg",
    "stargazers_count": 43,
    "open_issues_count": 2,
    "forks_count": 17
  },
  {
    "full_name": "vercel/hyper",
    "stargazers_count": 40031,
    "open_issues_count": 862,
    "forks_count": 3336
  },
  {
    "full_name": "mas-cli/mas",
    "stargazers_count": 9467,
    "open_issues_count": 76,
    "forks_count": 244
  },
  {
    "full_name": "dokeraj/AndroTainer",
    "stargazers_count": 71,
    "open_issues_count": 7,
    "forks_count": 5
  },
  {
    "full_name": "cheat/cheat",
    "stargazers_count": 10450,
    "open_issues_count": 33,
    "forks_count": 774
  },
  {
    "full_name": "httpie/httpie",
    "stargazers_count": 25530,
    "open_issues_count": 134,
    "forks_count": 3729
  },
  {
    "full_name": "ducaale/xh",
    "stargazers_count": 3387,
    "open_issues_count": 34,
    "forks_count": 68
  },
  {
    "full_name": "ogham/dog",
    "stargazers_count": 4816,
    "open_issues_count": 63,
    "forks_count": 119
  },
  {
    "full_name": "pacstall/pacstall",
    "stargazers_count": 764,
    "open_issues_count": 37,
    "forks_count": 24
  },
  {
    "full_name": "piraces/tldr-extension-browser",
    "stargazers_count": 10,
    "open_issues_count": 0,
    "forks_count": 1
  },
  {
    "full_name": "zyedidia/micro",
    "stargazers_count": 20853,
    "open_issues_count": 730,
    "forks_count": 1081
  },
  {
    "full_name": "lgallard/qBittorrent-Controller",
    "stargazers_count": 263,
    "open_issues_count": 60,
    "forks_count": 58
  },
  {
    "full_name": "botallen/repository.botallen",
    "stargazers_count": 246,
    "open_issues_count": 104,
    "forks_count": 105
  },
  {
    "full_name": "AmruthPillai/Reactive-Resume",
    "stargazers_count": 9850,
    "open_issues_count": 122,
    "forks_count": 1161
  }
]