[
  {
    "full_name": "google/sanitizers",
    "stargazers_count": 11626,
    "open_issues_count": 655,
    "forks_count": 1045
  },
  {
    "full_name": "Domi04151309/BatteryTool",
    "stargazers_count": 115,
    "open_issues_count": 6,
    "forks_count": 12
  },
  {
    "full_name": "fynks/awesome-android-root",
    "stargazers_count": 303,
    "open_issues_count": 1,
    "forks_count": 13
  },
  {
    "full_name": "tortuvshin/open-source-flutter-apps",
    "stargazers_count": 3956,
    "open_issues_count": 7,
    "forks_count": 747
  },
  {
    "full_name": "grafana/grafana",
    "stargazers_count": 65580,
    "open_issues_count": 4235,
    "forks_count": 12237
  },
  {
    "full_name": "syncthing/syncthing",
    "stargazers_count": 66283,
    "open_issues_count": 389,
    "forks_count": 4343
  },
  {
    "full_name": "gnuradio/gnuradio",
    "stargazers_count": 5173,
    "open_issues_count": 491,
    "forks_count": 1924
  },
  {
    "full_name": "albertomosconi/foss-apps",
    "stargazers_count": 723,
    "open_issues_count": 9,
    "forks_count": 26
  },
  {
    "full_name": "Asabeneh/30-Days-Of-Python",
    "stargazers_count": 43400,
    "open_issues_count": 198,
    "forks_count": 8289
  },
  {
    "full_name": "521xueweihan/HelloGitHub",
    "stargazers_count": 96103,
    "open_issues_count": 176,
    "forks_count": 9727
  },
  {
    "full_name": "warpdotdev/Warp",
    "stargazers_count": 21699,
    "open_issues_count": 2331,
    "forks_count": 382
  },
  {
    "full_name": "kingToolbox/WindTerm",
    "stargazers_count": 24169,
    "open_issues_count": 1883,
    "forks_count": 1852
  },
  {
    "full_name": "withfig/autocomplete",
    "stargazers_count": 24631,
    "open_issues_count": 171,
    "forks_count": 5512
  },
  {
    "full_name": "microsoft/calculator",
    "stargazers_count": 29914,
    "open_issues_count": 374,
    "forks_count": 5449
  },
  {
    "full_name": "doocs/leetcode",
    "stargazers_count": 32187,
    "open_issues_count": 9,
    "forks_count": 7796
  },
  {
    "full_name": "androiddevnotes/awesome-android-learning-resources",
    "stargazers_count": 1731,
    "open_issues_count": 10,
    "forks_count": 262
  },
  {
    "full_name": "JakubVojvoda/design-patterns-cpp",
    "stargazers_count": 4241,
    "open_issues_count": 4,
    "forks_count": 948
  },
  {
    "full_name": "DataExpert-io/data-engineer-handbook",
    "stargazers_count": 23510,
    "open_issues_count": 8,
    "forks_count": 4036
  },
  {
    "full_name": "trungdq88/Awesome-Black-Friday-Cyber-Monday",
    "stargazers_count": 5995,
    "open_issues_count": 7,
    "forks_count": 1207
  },
  {
    "full_name": "JioTV-Go/jiotv_go",
    "stargazers_count": 404,
    "open_issues_count": 12,
    "forks_count": 101
  },
  {
    "full_name": "gto76/python-cheatsheet",
    "stargazers_count": 36617,
    "open_issues_count": 23,
    "forks_count": 6483
  },
  {
    "full_name": "pyenv/pyenv",
    "stargazers_count": 39927,
    "open_issues_count": 66,
    "forks_count": 3076
  },
  {
    "full_name": "azl397985856/leetcode",
    "stargazers_count": 54860,
    "open_issues_count": 10,
    "forks_count": 9471
  },
  {
    "full_name": "scikit-learn/scikit-learn",
    "stargazers_count": 60513,
    "open_issues_count": 2102,
    "forks_count": 25467
  },
  {
    "full_name": "tensorflow/tensorflow",
    "stargazers_count": 186881,
    "open_issues_count": 6167,
    "forks_count": 74378
  },
  {
    "full_name": "jopohl/urh",
    "stargazers_count": 11075,
    "open_issues_count": 46,
    "forks_count": 881
  },
  {
    "full_name": "flameshot-org/flameshot",
    "stargazers_count": 25232,
    "open_issues_count": 756,
    "forks_count": 1611
  },
  {
    "full_name": "qutebrowser/qutebrowser",
    "stargazers_count": 9948,
    "open_issues_count": 1228,
    "forks_count": 1019
  },
  {
    "full_name": "dail8859/NotepadNext",
    "stargazers_count": 9348,
    "open_issues_count": 58,
    "forks_count": 562
  },
  {
    "full_name": "JesseTG/awesome-qt",
    "stargazers_count": 1442,
    "open_issues_count": 12,
    "forks_count": 184
  }
]