[
  {
    "full_name": "zed-industries/zed",
    "stargazers_count": 39245,
    "open_issues_count": 2213,
    "forks_count": 2034
  },
  {
    "full_name": "markedjs/marked",
    "stargazers_count": 32297,
    "open_issues_count": 26,
    "forks_count": 3364
  },
  {
    "full_name": "tree-sitter/tree-sitter",
    "stargazers_count": 17164,
    "open_issues_count": 346,
    "forks_count": 1264
  },
  {
    "full_name": "isocpp/CppCoreGuidelines",
    "stargazers_count": 41956,
    "open_issues_count": 244,
    "forks_count": 5399
  },
  {
    "full_name": "proj3rd/proj3rd",
    "stargazers_count": 3,
    "open_issues_count": 0,
    "forks_count": 0
  },
  {
    "full_name": "alexanderepstein/Bash-Snippets",
    "stargazers_count": 9559,
    "open_issues_count": 10,
    "forks_count": 845
  },
  {
    "full_name": "thibmaek/awesome-raspberry-pi",
    "stargazers_count": 13001,
    "open_issues_count": 3,
    "forks_count": 999
  },
  {
    "full_name": "stax76/awesome-mpv",
    "stargazers_count": 819,
    "open_issues_count": 3,
    "forks_count": 20
  },
  {
    "full_name": "mopidy/mopidy",
    "stargazers_count": 7972,
    "open_issues_count": 210,
    "forks_count": 685
  },
  {
    "full_name": "swiftlang/swift",
    "stargazers_count": 66674,
    "open_issues_count": 7396,
    "forks_count": 10279
  },
  {
    "full_name": "DerekSelander/LLDB",
    "stargazers_count": 1748,
    "open_issues_count": 13,
    "forks_count": 197
  },
  {
    "full_name": "iptv-org/awesome-iptv",
    "stargazers_count": 6473,
    "open_issues_count": 8,
    "forks_count": 753
  },
  {
    "full_name": "GigayasaWireless/toolkit5G",
    "stargazers_count": 26,
    "open_issues_count": 0,
    "forks_count": 6
  },
  {
    "full_name": "public-apis/public-apis",
    "stargazers_count": 297208,
    "open_issues_count": 285,
    "forks_count": 32236
  },
  {
    "full_name": "codecrafters-io/build-your-own-x",
    "stargazers_count": 280981,
    "open_issues_count": 337,
    "forks_count": 26368
  },
  {
    "full_name": "zhiwehu/Python-programming-exercises",
    "stargazers_count": 26287,
    "open_issues_count": 152,
    "forks_count": 6766
  },
  {
    "full_name": "viatsko/awesome-vscode",
    "stargazers_count": 24547,
    "open_issues_count": 69,
    "forks_count": 1203
  },
  {
    "full_name": "jpr5/ngrep",
    "stargazers_count": 862,
    "open_issues_count": 21,
    "forks_count": 99
  },
  {
    "full_name": "compiler-explorer/compiler-explorer",
    "stargazers_count": 15611,
    "open_issues_count": 750,
    "forks_count": 1660
  },
  {
    "full_name": "skills/introduction-to-github",
    "stargazers_count": 4127,
    "open_issues_count": 2,
    "forks_count": 1748
  },
  {
    "full_name": "Endava/cats",
    "stargazers_count": 1104,
    "open_issues_count": 5,
    "forks_count": 75
  },
  {
    "full_name": "mathiasbynens/dotfiles",
    "stargazers_count": 29993,
    "open_issues_count": 185,
    "forks_count": 8736
  },
  {
    "full_name": "solidiquis/erdtree",
    "stargazers_count": 2274,
    "open_issues_count": 28,
    "forks_count": 61
  },
  {
    "full_name": "rust-lang/rust",
    "stargazers_count": 94690,
    "open_issues_count": 10068,
    "forks_count": 12203
  },
  {
    "full_name": "my5G/my5G-RANTester",
    "stargazers_count": 92,
    "open_issues_count": 15,
    "forks_count": 31
  },
  {
    "full_name": "esnet/iperf",
    "stargazers_count": 6510,
    "open_issues_count": 193,
    "forks_count": 1252
  },
  {
    "full_name": "scrapy/scrapy",
    "stargazers_count": 51577,
    "open_issues_count": 661,
    "forks_count": 10411
  },
  {
    "full_name": "home-assistant/core",
    "stargazers_count": 69701,
    "open_issues_count": 2712,
    "forks_count": 28858
  },
  {
    "full_name": "pytorch/pytorch",
    "stargazers_count": 80001,
    "open_issues_count": 14273,
    "forks_count": 21510
  },
  {
    "full_name": "django/django",
    "stargazers_count": 77775,
    "open_issues_count": 228,
    "forks_count": 31180
  }
]